crc_8/hdl/crc_8.sv
`timescale 1ns / 1ps

//////////////////////////////////////////////////////////////////////////////////
//
// Engineer: Michael Fallon
//
// Design Name: crc_8
// Module Name: fm_synth_top
// Tool Versions: Vivado 2020.2
//
// Description: This module receives data from phy using standard MII protocol.
// Data is received in nibbles and sent out as bytes, along with a byte valid 
// flag to indicate a valid byte. The MII protocol specifies that data is received
// Most Significant Byte first, but within that byte, the Least Significant Nibble
// is received first, followed by the Most significant nibble. So if the following
// data is seen on rx_data : 0xA 0xC 0x4 0xD then the intended bytes are 0xCA 0xD4
//
// Note that the MAC address for the PHY must be provided with the nibbles
// inverted in order to conform to the MII receive data format
//
// crc[31:0]=1+x^1+x^2+x^4+x^5+x^7+x^8+x^10+x^11+x^12+x^16+x^22+x^23+x^26+x^32;
//
//////////////////////////////////////////////////////////////////////////////////

module crc_8 #(
    parameter [31:0]    P_RESIDUE = 32'hC704DD7B
    )(
    input   logic           clk,
    input   logic           rst_n,
    input   logic   [7:0]   data_in,
    input   logic           data_in_vld,
    input   logic           byte_in_vld,
    output  logic           crc_vld
    );

    wire    [7:0]   data;
    reg     [31:0]  crc_q;
    reg     [31:0]  crc_d;
    genvar          i;

    assign crc_vld = (crc_d == P_RESIDUE) & byte_in_vld;

    generate
        for (i=0; i<8; i=i+1)
            assign data[i]  = data_in[7-i];
    endgenerate

    always @(posedge clk) begin
        if(~rst_n) begin
            crc_q <= ~0;
        end

        else begin
            if (byte_in_vld) begin
                crc_q   <= data_in_vld ? crc_d : ~0;
            end
        end
    end

    always @(*) begin
        crc_d[0]  = crc_q[24] ^ crc_q[30] ^ data[0]   ^ data[6];
        crc_d[1]  = crc_q[24] ^ crc_q[25] ^ crc_q[30] ^ crc_q[31] ^ data[0]   ^ data[1]   ^ data[6]   ^ data[7];
        crc_d[2]  = crc_q[24] ^ crc_q[25] ^ crc_q[26] ^ crc_q[30] ^ crc_q[31] ^ data[0]   ^ data[1]   ^ data[2] ^ data[6] ^ data[7];
        crc_d[3]  = crc_q[25] ^ crc_q[26] ^ crc_q[27] ^ crc_q[31] ^ data[1]   ^ data[2]   ^ data[3]   ^ data[7];
        crc_d[4]  = crc_q[24] ^ crc_q[26] ^ crc_q[27] ^ crc_q[28] ^ crc_q[30] ^ data[0]   ^ data[2]   ^ data[3] ^ data[4] ^ data[6];
        crc_d[5]  = crc_q[24] ^ crc_q[25] ^ crc_q[27] ^ crc_q[28] ^ crc_q[29] ^ crc_q[30] ^ crc_q[31] ^ data[0] ^ data[1] ^ data[3] ^ data[4] ^ data[5] ^ data[6] ^ data[7];
        crc_d[6]  = crc_q[25] ^ crc_q[26] ^ crc_q[28] ^ crc_q[29] ^ crc_q[30] ^ crc_q[31] ^ data[1]   ^ data[2] ^ data[4] ^ data[5] ^ data[6] ^ data[7];
        crc_d[7]  = crc_q[24] ^ crc_q[26] ^ crc_q[27] ^ crc_q[29] ^ crc_q[31] ^ data[0]   ^ data[2]   ^ data[3] ^ data[5] ^ data[7];
        crc_d[8]  = crc_q[0]  ^ crc_q[24] ^ crc_q[25] ^ crc_q[27] ^ crc_q[28] ^ data[0]   ^ data[1]   ^ data[3] ^ data[4];
        crc_d[9]  = crc_q[1]  ^ crc_q[25] ^ crc_q[26] ^ crc_q[28] ^ crc_q[29] ^ data[1]   ^ data[2]   ^ data[4] ^ data[5];
        crc_d[10] = crc_q[2]  ^ crc_q[24] ^ crc_q[26] ^ crc_q[27] ^ crc_q[29] ^ data[0]   ^ data[2]   ^ data[3] ^ data[5];
        crc_d[11] = crc_q[3]  ^ crc_q[24] ^ crc_q[25] ^ crc_q[27] ^ crc_q[28] ^ data[0]   ^ data[1]   ^ data[3] ^ data[4];
        crc_d[12] = crc_q[4]  ^ crc_q[24] ^ crc_q[25] ^ crc_q[26] ^ crc_q[28] ^ crc_q[29] ^ crc_q[30] ^ data[0] ^ data[1] ^ data[2] ^ data[4] ^ data[5] ^ data[6];
        crc_d[13] = crc_q[5]  ^ crc_q[25] ^ crc_q[26] ^ crc_q[27] ^ crc_q[29] ^ crc_q[30] ^ crc_q[31] ^ data[1] ^ data[2] ^ data[3] ^ data[5] ^ data[6] ^ data[7];
        crc_d[14] = crc_q[6]  ^ crc_q[26] ^ crc_q[27] ^ crc_q[28] ^ crc_q[30] ^ crc_q[31] ^ data[2]   ^ data[3] ^ data[4] ^ data[6] ^ data[7];
        crc_d[15] = crc_q[7]  ^ crc_q[27] ^ crc_q[28] ^ crc_q[29] ^ crc_q[31] ^ data[3]   ^ data[4]   ^ data[5] ^ data[7];
        crc_d[16] = crc_q[8]  ^ crc_q[24] ^ crc_q[28] ^ crc_q[29] ^ data[0]   ^ data[4]   ^ data[5];
        crc_d[17] = crc_q[9]  ^ crc_q[25] ^ crc_q[29] ^ crc_q[30] ^ data[1]   ^ data[5]   ^ data[6];
        crc_d[18] = crc_q[10] ^ crc_q[26] ^ crc_q[30] ^ crc_q[31] ^ data[2]   ^ data[6]   ^ data[7];
        crc_d[19] = crc_q[11] ^ crc_q[27] ^ crc_q[31] ^ data[3]   ^ data[7];
        crc_d[20] = crc_q[12] ^ crc_q[28] ^ data[4];
        crc_d[21] = crc_q[13] ^ crc_q[29] ^ data[5];
        crc_d[22] = crc_q[14] ^ crc_q[24] ^ data[0];
        crc_d[23] = crc_q[15] ^ crc_q[24] ^ crc_q[25] ^ crc_q[30] ^ data[0]   ^ data[1] ^ data[6];
        crc_d[24] = crc_q[16] ^ crc_q[25] ^ crc_q[26] ^ crc_q[31] ^ data[1]   ^ data[2] ^ data[7];
        crc_d[25] = crc_q[17] ^ crc_q[26] ^ crc_q[27] ^ data[2]   ^ data[3];
        crc_d[26] = crc_q[18] ^ crc_q[24] ^ crc_q[27] ^ crc_q[28] ^ crc_q[30] ^ data[0] ^ data[3] ^ data[4] ^ data[6];
        crc_d[27] = crc_q[19] ^ crc_q[25] ^ crc_q[28] ^ crc_q[29] ^ crc_q[31] ^ data[1] ^ data[4] ^ data[5] ^ data[7];
        crc_d[28] = crc_q[20] ^ crc_q[26] ^ crc_q[29] ^ crc_q[30] ^ data[2]   ^ data[5] ^ data[6];
        crc_d[29] = crc_q[21] ^ crc_q[27] ^ crc_q[30] ^ crc_q[31] ^ data[3]   ^ data[6] ^ data[7];
        crc_d[30] = crc_q[22] ^ crc_q[28] ^ crc_q[31] ^ data[4]   ^ data[7];
        crc_d[31] = crc_q[23] ^ crc_q[29] ^ data[5];
    end
    
    initial begin
        $dumpfile("crc_8.vcd");
        $dumpvars();
    end


endmodule

crc_8/test/sim_build/crc_8.vcd
$date
	Sat Jan 13 10:27:17 2024
$end
$version
	Icarus Verilog
$end
$timescale
	1ps
$end
$scope module crc_8 $end
$var wire 1 ! byte_in_vld $end
$var wire 1 " clk $end
$var wire 1 # crc_vld $end
$var wire 8 $ data_in [7:0] $end
$var wire 1 % data_in_vld $end
$var wire 1 & rst_n $end
$var wire 8 ' data [7:0] $end
$var parameter 32 ( P_RESIDUE $end
$var reg 32 ) crc_d [31:0] $end
$var reg 32 * crc_q [31:0] $end
$scope begin genblk1[0] $end
$var parameter 2 + i $end
$upscope $end
$scope begin genblk1[1] $end
$var parameter 2 , i $end
$upscope $end
$scope begin genblk1[2] $end
$var parameter 3 - i $end
$upscope $end
$scope begin genblk1[3] $end
$var parameter 3 . i $end
$upscope $end
$scope begin genblk1[4] $end
$var parameter 4 / i $end
$upscope $end
$scope begin genblk1[5] $end
$var parameter 4 0 i $end
$upscope $end
$scope begin genblk1[6] $end
$var parameter 4 1 i $end
$upscope $end
$scope begin genblk1[7] $end
$var parameter 4 2 i $end
$upscope $end
$upscope $end
$enddefinitions $end
$comment Show the parameter values. $end
$dumpall
b111 2
b110 1
b101 0
b100 /
b11 .
b10 -
b1 ,
b0 +
b11000111000001001101110101111011 (
$end
#0
$dumpvars
b11111111111111111111111111111111 *
b1001110000010001011111110110100 )
b0 '
0&
0%
b0 $
0#
1"
1!
$end
#5000
0"
#10000
0!
1&
1"
#15000
0"
#20000
1!
1"
#25000
0"
#30000
0!
1"
#35000
0"
#40000
1!
1"
#45000
0"
#50000
0!
1"
#55000
0"
#60000
1!
1"
#65000
0"
#70000
0!
1"
#75000
0"
#80000
1!
1"
#85000
0"
#90000
0!
1"
#95000
0"
#100000
1!
1"
#105000
0"
#110000
0!
1"
#115000
0"
#120000
1!
1"
#125000
0"
#130000
0!
1"
#135000
0"
#140000
1!
1"
#145000
0"
#150000
0!
1"
#155000
0"
#160000
1!
1"
#165000
0"
#170000
0!
1"
#175000
0"
#180000
1!
1"
#185000
0"
#190000
0!
1"
#195000
0"
#200000
1!
1"
#205000
0"
#210000
0!
1"
#215000
0"
#220000
1!
1"
#225000
0"
#230000
0!
1"
#235000
0"
#240000
1!
1"
#245000
0"
#250000
0!
1"
#255000
0"
#260000
1!
1"
#265000
0"
#270000
0!
1"
#275000
0"
#280000
1!
1"
#285000
0"
#290000
0!
1"
#295000
0"
#300000
1!
1"
#305000
0"
#310000
0!
1"
#315000
0"
#320000
1!
1"
#325000
0"
#330000
0!
1"
#335000
0"
#340000
1!
1"
#345000
0"
#350000
0!
1"
#355000
0"
#360000
1!
1"
#365000
0"
#370000
0!
1"
#375000
0"
#380000
1!
1"
#385000
0"
#390000
0!
1"
#395000
0"
#400000
1!
1"
#405000
0"
#410000
0!
1"
#415000
0"
#420000
1!
1"
#425000
0"
#430000
0!
1"
#435000
0"
#440000
1!
1"
#445000
0"
#450000
0!
1"
#455000
0"
#460000
1!
1"
#465000
0"
#470000
0!
1"
#475000
0"
#480000
1!
1"
#485000
0"
#490000
0!
1"
#495000
0"
#500000
1!
1"
#505000
0"
#510000
0!
1"
#515000
0"
#520000
1!
1"
#525000
0"
#530000
0!
1"
#535000
0"
#540000
1!
1"
#545000
0"
#550000
0!
1"
#555000
0"
#560000
1!
1"
#565000
0"
#570000
0!
1"
#575000
0"
#580000
1!
1"
#585000
0"
#590000
0!
1"
#595000
0"
#600000
1!
1"
#605000
0"
#610000
0!
1"
#615000
0"
#620000
1!
1"
#625000
0"
#630000
0!
1"
#635000
0"
#640000
1!
1"
#645000
0"
#650000
0!
1"
#655000
0"
#660000
1!
1"
#665000
0"
#670000
0!
1"
#675000
0"
#680000
1!
1"
#685000
0"
#690000
0!
1"
#695000
0"
#700000
1!
1"
#705000
0"
#710000
0!
1"
#715000
0"
#720000
1!
1"
#725000
0"
#730000
0!
1"
#735000
0"
#740000
1!
1"
#745000
0"
#750000
0!
1"
#755000
0"
#760000
1!
1"
#765000
0"
#770000
0!
1"
#775000
0"
#780000
1!
1"
#785000
0"
#790000
0!
1"
#795000
0"
#800000
1!
1"
#805000
0"
#810000
0!
1"
#815000
0"
#820000
1!
1"
#825000
0"
#830000
0!
1"
#835000
0"
#840000
1!
1"
#845000
0"
#850000
0!
1"
#855000
0"
#860000
1!
1"
#865000
0"
#870000
0!
1"
#875000
0"
#880000
1!
1"
#885000
0"
#890000
0!
1"
#895000
0"
#900000
1!
1"
#905000
0"
#910000
0!
1"
#915000
0"
#920000
1!
1"
#925000
0"
#930000
0!
1"
#935000
0"
#940000
1!
1"
#945000
0"
#950000
0!
1"
#955000
0"
#960000
1!
1"
#965000
0"
#970000
0!
1"
#975000
0"
#980000
1!
1"
#985000
0"
#990000
b100111000001000101111101011010 )
b10000000 '
b1 $
1%
0!
1"
#995000
0"
#1000000
1!
1"
#1005000
0"
#1010000
b0 '
b0 $
0!
b10000010001110111011110011100101 )
b100111000001000101111101011010 *
1"
#1015000
0"
#1020000
1!
1"
#1025000
0"
#1030000
b1111010 '
b1011110 $
0!
b10010100000011001111010110110001 )
b10000010001110111011110011100101 *
1"
#1035000
0"
#1040000
1!
1"
#1045000
0"
#1050000
b10100 '
b101000 $
0!
b1100101111110010101000111101110 )
b10010100000011001111010110110001 *
1"
#1055000
0"
#1060000
1!
1"
#1065000
0"
#1070000
b100110 '
b1100100 $
0!
b11000000100101001011100010101110 )
b1100101111110010101000111101110 *
1"
#1075000
0"
#1080000
1!
1"
#1085000
0"
#1090000
b10000000 '
b1 $
0!
b10100000001111101101111001110111 )
b11000000100101001011100010101110 *
1"
#1095000
0"
#1100000
1!
1"
#1105000
0"
#1110000
b110100 '
b101100 $
0!
b1000110001110011101001000010 )
b10100000001111101101111001110111 *
1"
#1115000
0"
#1120000
1!
1"
#1125000
0"
#1130000
b1011111 '
b11111010 $
0!
b10100001111010101011100100000010 )
b1000110001110011101001000010 *
1"
#1135000
0"
#1140000
1!
1"
#1145000
0"
#1150000
b1000101 '
b10100010 $
0!
b111100000101000101001010100101 )
b10100001111010101011100100000010 *
1"
#1155000
0"
#1160000
1!
1"
#1165000
0"
#1170000
b11100101 '
b10100111 $
0!
b100111000000000001111011100110 )
b111100000101000101001010100101 *
1"
#1175000
0"
#1180000
1!
1"
#1185000
0"
#1190000
b11110010 '
b1001111 $
0!
b110010000001100011010000010 )
b100111000000000001111011100110 *
1"
#1195000
0"
#1200000
1!
1"
#1205000
0"
#1210000
b10000001 '
b10000001 $
0!
b110111100011010011001011101011 )
b110010000001100011010000010 *
1"
#1215000
0"
#1220000
1!
1"
#1225000
0"
#1230000
b10000 '
b1000 $
0!
b1011010101100000110111100101 )
b110111100011010011001011101011 *
1"
#1235000
0"
#1240000
1!
1"
#1245000
0"
#1250000
b0 '
b0 $
0!
b1111101010001100010111001100001 )
b1011010101100000110111100101 *
1"
#1255000
0"
#1260000
1!
1"
#1265000
0"
#1270000
b1100010 '
b1000110 $
0!
b110010011100000000011111001101 )
b1111101010001100010111001100001 *
1"
#1275000
0"
#1280000
1!
1"
#1285000
0"
#1290000
b11 '
b11000000 $
0!
b10100000111101001011110100100111 )
b110010011100000000011111001101 *
1"
#1295000
0"
#1300000
1!
1"
#1305000
0"
#1310000
b0 '
b0 $
0!
b101100100100111000100001110 )
b10100000111101001011110100100111 *
1"
#1315000
0"
#1320000
1!
1"
#1325000
0"
#1330000
b100 '
b100000 $
0!
b10010110101100000001001110110111 )
b101100100100111000100001110 *
1"
#1335000
0"
#1340000
1!
1"
#1345000
0"
#1350000
b1100011 '
b11000110 $
0!
b101110011011100010000101100010 )
b10010110101100000001001110110111 *
1"
#1355000
0"
#1360000
1!
1"
#1365000
0"
#1370000
b10010011 '
b11001001 $
0!
b11100010110100100110100110101101 )
b101110011011100010000101100010 *
1"
#1375000
0"
#1380000
1!
1"
#1385000
0"
#1390000
b0 '
b0 $
0!
b11110010000101011000000010111 )
b11100010110100100110100110101101 *
1"
#1395000
0"
#1400000
1!
1"
#1405000
0"
#1410000
0!
b110010001011110110110001111010 )
b11110010000101011000000010111 *
1"
#1415000
0"
#1420000
1!
1"
#1425000
0"
#1430000
b10000000 '
b1 $
0!
b10011011110100001100110000010000 )
b110010001011110110110001111010 *
1"
#1435000
0"
#1440000
1!
1"
#1445000
0"
#1450000
b1000000 '
b10 $
0!
b11101010000111001001000010001000 )
b10011011110100001100110000010000 *
1"
#1455000
0"
#1460000
1!
1"
#1465000
0"
#1470000
b101111 '
b11110100 $
0!
b1010110110111110111001111110010 )
b11101010000111001001000010001000 *
1"
#1475000
0"
#1480000
1!
1"
#1485000
0"
#1490000
b1100111 '
b11100110 $
0!
b1111100000001000001000100111 )
b1010110110111110111001111110010 *
1"
#1495000
0"
#1500000
1!
1"
#1505000
0"
#1510000
b1000001 '
b10000010 $
0!
b10001000100010101111011101111101 )
b1111100000001000001000100111 *
1"
#1515000
0"
#1520000
1!
1"
#1525000
0"
#1530000
b11111101 '
b10111111 $
0!
b1111101100001100000101110001100 )
b10001000100010101111011101111101 *
1"
#1535000
0"
#1540000
1!
1"
#1545000
0"
#1550000
b101 '
b10100000 $
0!
b1000000101101110111110001011111 )
b1111101100001100000101110001100 *
1"
#1555000
0"
#1560000
1!
1"
#1565000
0"
#1570000
b1111111 '
b11111110 $
0!
b1011011000000011000111100101101 )
b1000000101101110111110001011111 *
1"
#1575000
0"
#1580000
1!
1"
#1585000
0"
#1590000
b111 '
b11100000 $
0!
b1001100000101000001110101100011 )
b1011011000000011000111100101101 *
1"
#1595000
0"
#1600000
1!
1"
#1605000
0"
#1610000
b10101 '
b10101000 $
0!
b1001110010000110011100000001000 )
b1001100000101000001110101100011 *
1"
#1615000
0"
#1620000
1!
1"
#1625000
0"
#1630000
b100110 '
b1100100 $
0!
b11001001100101010010001100101111 )
b1001110010000110011100000001000 *
1"
#1635000
0"
#1640000
1!
1"
#1645000
0"
#1650000
b10000000 '
b1 $
0!
b10000011011011001010111101111000 )
b11001001100101010010001100101111 *
1"
#1655000
0"
#1660000
1!
1"
#1665000
0"
#1670000
b101001 '
b10010100 $
0!
b10110010000010101111100011011000 )
b10000011011011001010111101111000 *
1"
#1675000
0"
#1680000
1!
1"
#1685000
0"
#1690000
b100000 '
b100 $
0!
b100110011001111101100011110000 )
b10110010000010101111100011011000 *
1"
#1695000
0"
#1700000
1!
1"
#1705000
0"
#1710000
b0 '
b0 $
0!
b11100101011111010000101101010010 )
b100110011001111101100011110000 *
1"
#1715000
0"
#1720000
1!
1"
#1725000
0"
#1730000
0!
b10101111011001110001111100010010 )
b11100101011111010000101101010010 *
1"
#1735000
0"
#1740000
1!
1"
#1745000
0"
#1750000
b10001000 '
b10001 $
0!
b11100001011110111111010011100101 )
b10101111011001110001111100010010 *
1"
#1755000
0"
#1760000
1!
1"
#1765000
0"
#1770000
b1010000 '
b1010 $
0!
b11000010000010110111010111001001 )
b11100001011110111111010011100101 *
1"
#1775000
0"
#1780000
1!
1"
#1785000
0"
#1790000
b1010101 '
b10101010 $
0!
b110000001011111010001010011011 )
b11000010000010110111010111001001 *
1"
#1795000
0"
#1800000
1!
1"
#1805000
0"
#1810000
b11010010 '
b1001011 $
0!
b11100011100010011000011000010111 )
b110000001011111010001010011011 *
1"
#1815000
0"
#1820000
1!
1"
#1825000
0"
#1830000
b111 '
b11100000 $
0!
b1011111001010110100011110100101 )
b11100011100010011000011000010111 *
1"
#1835000
0"
#1840000
1!
1"
#1845000
0"
#1850000
b10101 '
b10101000 $
0!
b110000010010110000001110100001 )
b1011111001010110100011110100101 *
1"
#1855000
0"
#1860000
1!
1"
#1865000
0"
#1870000
b100110 '
b1100100 $
0!
b11101100101000011011111000010 )
b110000010010110000001110100001 *
1"
#1875000
0"
#1880000
1!
1"
#1885000
0"
#1890000
b10000000 '
b1 $
0!
b10000000111001110111111101001101 )
b11101100101000011011111000010 *
1"
#1895000
0"
#1900000
1!
1"
#1905000
0"
#1910000
b0 '
b0 $
0!
b10001110011100111010110111101110 )
b10000000111001110111111101001101 *
1"
#1915000
0"
#1920000
1!
1"
#1925000
0"
#1930000
0!
b100110001011111010111011100100 )
b10001110011100111010110111101110 *
1"
#1935000
0"
#1940000
1!
1"
#1945000
0"
#1950000
0!
b10101101000010110001111101010010 )
b100110001011111010111011100100 *
1"
#1955000
0"
#1960000
1!
1"
#1965000
0"
#1970000
0!
b11001011111111011000001011011101 )
b10101101000010110001111101010010 *
1"
#1975000
0"
#1980000
1!
1"
#1985000
0"
#1990000
0!
b10001011010000111000011011111000 )
b11001011111111011000001011011101 *
1"
#1995000
0"
#2000000
1!
1"
#2005000
0"
#2010000
0!
b1110000011101001110001111 )
b10001011010000111000011011111000 *
1"
#2015000
0"
#2020000
1!
1"
#2025000
0"
#2030000
0!
b11000101000100101001001010110111 )
b1110000011101001110001111 *
1"
#2035000
0"
#2040000
1!
1"
#2045000
0"
#2050000
0!
b1011000110111010100110011110010 )
b11000101000100101001001010110111 *
1"
#2055000
0"
#2060000
1!
1"
#2065000
0"
#2070000
0!
b10000011110100111011010010111111 )
b1011000110111010100110011110010 *
1"
#2075000
0"
#2080000
1!
1"
#2085000
0"
#2090000
0!
b10110111111110110111100100110111 )
b10000011110100111011010010111111 *
1"
#2095000
0"
#2100000
1!
1"
#2105000
0"
#2110000
0!
b1011000000000001110101001111011 )
b10110111111110110111100100110111 *
1"
#2115000
0"
#2120000
1!
1"
#2125000
0"
#2130000
0!
b1011110011101010011110110111111 )
b1011000000000001110101001111011 *
1"
#2135000
0"
#2140000
1!
1"
#2145000
0"
#2150000
0!
b110001001001001011010000001101 )
b1011110011101010011110110111111 *
1"
#2155000
0"
#2160000
1!
1"
#2165000
0"
#2170000
0!
b11110100010001110111110100100111 )
b110001001001001011010000001101 *
1"
#2175000
0"
#2180000
1!
1"
#2185000
0"
#2190000
b1011 '
b11010000 $
0!
b11110110100010100110011110110100 )
b11110100010001110111110100100111 *
1"
#2195000
0"
#2200000
1!
1"
#2205000
0"
#2210000
b10111000 '
b11101 $
0!
b10000010011011110110010001111101 )
b11110110100010100110011110110100 *
1"
#2215000
0"
#2220000
1!
1"
#2225000
0"
#2230000
b10000010 '
b1000001 $
0!
b1101111011001000111110100000000 )
b10000010011011110110010001111101 *
1"
#2235000
0"
#2240000
1!
1"
#2245000
0"
#2250000
b11011000 '
b11011 $
0!
b11000111000001001101110101111011 )
b1101111011001000111110100000000 *
1"
#2255000
0"
#2260000
1#
1!
1"
#2265000
0"
#2270000
b0 '
b0 $
0%
0!
0#
b1000111000100001011101110011100 )
b11000111000001001101110101111011 *
1"
#2275000
0"
#2280000
1!
1"
#2285000
0"
#2290000
0!
b1001110000010001011111110110100 )
b11111111111111111111111111111111 *
1"
#2295000
0"
#2300000
1!
1"
#2305000
0"
#2310000
0!
1"
#2315000
0"
#2320000
1!
1"
#2325000
0"
#2330000
0!
1"
#2335000
0"
#2340000
1!
1"
#2345000
0"
#2350000
0!
1"
#2355000
0"
#2360000
1!
1"
#2365000
0"
#2370000
0!
1"
#2375000
0"
#2380000
1!
1"
#2385000
0"
#2390000
0!
1"
#2395000
0"
#2400000
1!
1"
#2405000
0"
#2410000
0!
1"
#2415000
0"
#2420000
1!
1"
#2425000
0"
#2430000
0!
1"
#2435000
0"
#2440000
1!
1"
#2445000
0"
#2450000
0!
1"
#2455000
0"
#2460000
1!
1"
#2465000
0"
#2470000
0!
1"
#2475000
0"
#2480000
1!
1"
#2485000
0"
#2490000
0!
1"
#2495000
0"
#2500000
1!
1"
#2505000
0"
#2510000
0!
1"
#2515000
0"
#2520000
1!
1"
#2525000
0"
#2530000
0!
1"
#2535000
0"
#2540000
1!
1"
#2545000
0"
#2550000
0!
1"
#2555000
0"
#2560000
1!
1"
#2565000
0"
#2570000
0!
1"
#2575000
0"
#2580000
1!
1"
#2585000
0"
#2590000
0!
1"
#2595000
0"
#2600000
1!
1"
#2605000
0"
#2610000
0!
1"
#2615000
0"
#2620000
1!
1"
#2625000
0"
#2630000
0!
1"
#2635000
0"
#2640000
1!
1"
#2645000
0"
#2650000
0!
1"
#2655000
0"
#2660000
1!
1"
#2665000
0"
#2670000
0!
1"
#2675000
0"
#2680000
1!
1"
#2685000
0"
#2690000
0!
1"
#2695000
0"
#2700000
1!
1"
#2705000
0"
#2710000
0!
1"
#2715000
0"
#2720000
1!
1"
#2725000
0"
#2730000
0!
1"
#2735000
0"
#2740000
1!
1"
#2745000
0"
#2750000
0!
1"
#2755000
0"
#2760000
1!
1"
#2765000
0"
#2770000
0!
1"
#2775000
0"
#2780000
1!
1"
#2785000
0"
#2790000
0!
1"
#2795000
0"
#2800000
1!
1"
#2805000
0"
#2810000
0!
1"
#2815000
0"
#2820000
1!
1"
#2825000
0"
#2830000
0!
1"
#2835000
0"
#2840000
1!
1"
#2845000
0"
#2850000
0!
1"
#2855000
0"
#2860000
1!
1"
#2865000
0"
#2870000
0!
1"
#2875000
0"
#2880000
1!
1"
#2885000
0"
#2890000
0!
1"
#2895000
0"
#2900000
1!
1"
#2905000
0"
#2910000
0!
1"
#2915000
0"
#2920000
1!
1"
#2925000
0"
#2930000
0!
1"
#2935000
0"
#2940000
1!
1"
#2945000
0"
#2950000
0!
1"
#2955000
0"
#2960000
1!
1"
#2965000
0"
#2970000
0!
1"
#2975000
0"
#2980000
1!
1"
#2985000
0"
#2990000
0!
1"
#2995000
0"
#3000000
1!
1"
#3005000
0"
#3010000
0!
1"
#3015000
0"
#3020000
1!
1"
#3025000
0"
#3030000
0!
1"
#3035000
0"
#3040000
1!
1"
#3045000
0"
#3050000
0!
1"
#3055000
0"
#3060000
1!
1"
#3065000
0"
#3070000
0!
1"
#3075000
0"
#3080000
1!
1"
#3085000
0"
#3090000
0!
1"
#3095000
0"
#3100000
1!
1"
#3105000
0"
#3110000
0!
1"
#3115000
0"
#3120000
1!
1"
#3125000
0"
#3130000
0!
1"
#3135000
0"
#3140000
1!
1"
#3145000
0"
#3150000
0!
1"
#3155000
0"
#3160000
1!
1"
#3165000
0"
#3170000
0!
1"
#3175000
0"
#3180000
1!
1"
#3185000
0"
#3190000
0!
1"
#3195000
0"
#3200000
1!
1"
#3205000
0"
#3210000
0!
1"
#3215000
0"
#3220000
1!
1"
#3225000
0"
#3230000
0!
1"
#3235000
0"
#3240000
1!
1"
#3245000
0"
#3250000
0!
1"
#3255000
0"
#3260000
1!
1"
